{
  "1주일": [
    {
      "날짜": "\"20250721\"",
      "시가": 67400.0,
      "고가": 68800.0,
      "저가": 67200.0,
      "종가": 67800.0,
      "거래량": 17723148
    },
    {
      "날짜": "\"20250722\"",
      "시가": 68100.0,
      "고가": 68500.0,
      "저가": 65600.0,
      "종가": 66000.0,
      "거래량": 20829006
    },
    {
      "날짜": "\"20250723\"",
      "시가": 66200.0,
      "고가": 66500.0,
      "저가": 64900.0,
      "종가": 66400.0,
      "거래량": 15687058
    },
    {
      "날짜": "\"20250724\"",
      "시가": 66500.0,
      "고가": 66800.0,
      "저가": 65900.0,
      "종가": 66000.0,
      "거래량": 12660193
    },
    {
      "날짜": "\"20250725\"",
      "시가": 65700.0,
      "고가": 66300.0,
      "저가": 65500.0,
      "종가": 65900.0,
      "거래량": 8045068
    }
  ],
  "1개월": [
    {
      "날짜": "\"20250627\"",
      "시가": 60100.0,
      "고가": 61600.0,
      "저가": 60000.0,
      "종가": 60800.0,
      "거래량": 17340470
    },
    {
      "날짜": "\"20250630\"",
      "시가": 61200.0,
      "고가": 61200.0,
      "저가": 59800.0,
      "종가": 59800.0,
      "거래량": 17110294
    },
    {
      "날짜": "\"20250701\"",
      "시가": 60400.0,
      "고가": 61100.0,
      "저가": 60200.0,
      "종가": 60200.0,
      "거래량": 13650991
    },
    {
      "날짜": "\"20250702\"",
      "시가": 60200.0,
      "고가": 60900.0,
      "저가": 59800.0,
      "종가": 60800.0,
      "거래량": 15047951
    },
    {
      "날짜": "\"20250703\"",
      "시가": 61300.0,
      "고가": 63800.0,
      "저가": 61100.0,
      "종가": 63800.0,
      "거래량": 32040639
    },
    {
      "날짜": "\"20250704\"",
      "시가": 64700.0,
      "고가": 64700.0,
      "저가": 63000.0,
      "종가": 63300.0,
      "거래량": 23748959
    },
    {
      "날짜": "\"20250707\"",
      "시가": 62900.0,
      "고가": 63300.0,
      "저가": 61700.0,
      "종가": 61700.0,
      "거래량": 17164708
    },
    {
      "날짜": "\"20250708\"",
      "시가": 61600.0,
      "고가": 62400.0,
      "저가": 61000.0,
      "종가": 61400.0,
      "거래량": 20213724
    },
    {
      "날짜": "\"20250709\"",
      "시가": 61400.0,
      "고가": 61400.0,
      "저가": 60200.0,
      "종가": 60400.0,
      "거래량": 17533415
    },
    {
      "날짜": "\"20250710\"",
      "시가": 60600.0,
      "고가": 61200.0,
      "저가": 60400.0,
      "종가": 61000.0,
      "거래량": 14768473
    },
    {
      "날짜": "\"20250711\"",
      "시가": 61300.0,
      "고가": 62800.0,
      "저가": 61200.0,
      "종가": 62600.0,
      "거래량": 19140650
    },
    {
      "날짜": "\"20250714\"",
      "시가": 62300.0,
      "고가": 62600.0,
      "저가": 61800.0,
      "종가": 62500.0,
      "거래량": 13563846
    },
    {
      "날짜": "\"20250715\"",
      "시가": 62300.0,
      "고가": 63800.0,
      "저가": 62000.0,
      "종가": 63700.0,
      "거래량": 18442202
    },
    {
      "날짜": "\"20250716\"",
      "시가": 63700.0,
      "고가": 64700.0,
      "저가": 63100.0,
      "종가": 64700.0,
      "거래량": 23042660
    },
    {
      "날짜": "\"20250717\"",
      "시가": 65900.0,
      "고가": 66800.0,
      "저가": 64400.0,
      "종가": 66700.0,
      "거래량": 39448683
    },
    {
      "날짜": "\"20250718\"",
      "시가": 67000.0,
      "고가": 67800.0,
      "저가": 66300.0,
      "종가": 67100.0,
      "거래량": 23951531
    },
    {
      "날짜": "\"20250721\"",
      "시가": 67400.0,
      "고가": 68800.0,
      "저가": 67200.0,
      "종가": 67800.0,
      "거래량": 17723148
    },
    {
      "날짜": "\"20250722\"",
      "시가": 68100.0,
      "고가": 68500.0,
      "저가": 65600.0,
      "종가": 66000.0,
      "거래량": 20829006
    },
    {
      "날짜": "\"20250723\"",
      "시가": 66200.0,
      "고가": 66500.0,
      "저가": 64900.0,
      "종가": 66400.0,
      "거래량": 15687058
    },
    {
      "날짜": "\"20250724\"",
      "시가": 66500.0,
      "고가": 66800.0,
      "저가": 65900.0,
      "종가": 66000.0,
      "거래량": 12660193
    },
    {
      "날짜": "\"20250725\"",
      "시가": 65700.0,
      "고가": 66300.0,
      "저가": 65500.0,
      "종가": 65900.0,
      "거래량": 8045068
    }
  ],
  "기술적지표": {
    "날짜": "\"20250725\"",
    "시가": 65700.0,
    "고가": 66300.0,
    "저가": 65500.0,
    "종가": 65900.0,
    "거래량": 8045068,
    "MA5": 66420.0,
    "MA20": 63590.0,
    "MA60": NaN,
    "RSI": 68.10344827586208,
    "BB_MA20": 63590.0,
    "BB_STD": 2585.363661684342,
    "BB_UPPER": 68760.72732336869,
    "BB_LOWER": 58419.27267663131,
    "MACD": 860.8821285539016,
    "MACD_SIGNAL": 711.8758199772185,
    "VOLUME_MA5": 14988894.6,
    "VOLUME_MA20": 19190659.95
  },
  "3개월": [
    {
      "날짜": "\"20250428\"",
      "시가": 55800.0,
      "고가": 55900.0,
      "저가": 55500.0,
      "종가": 55800.0,
      "거래량": 9341518
    },
    {
      "날짜": "\"20250429\"",
      "시가": 55700.0,
      "고가": 56500.0,
      "저가": 55600.0,
      "종가": 55800.0,
      "거래량": 10295518
    },
    {
      "날짜": "\"20250430\"",
      "시가": 55900.0,
      "고가": 56000.0,
      "저가": 55300.0,
      "종가": 55500.0,
      "거래량": 13014189
    },
    {
      "날짜": "\"20250502\"",
      "시가": 55000.0,
      "고가": 55500.0,
      "저가": 54200.0,
      "종가": 54300.0,
      "거래량": 22454204
    },
    {
      "날짜": "\"20250507\"",
      "시가": 54500.0,
      "고가": 55000.0,
      "저가": 54300.0,
      "종가": 54600.0,
      "거래량": 17136991
    },
    {
      "날짜": "\"20250508\"",
      "시가": 55100.0,
      "고가": 55500.0,
      "저가": 54500.0,
      "종가": 54600.0,
      "거래량": 16320532
    },
    {
      "날짜": "\"20250509\"",
      "시가": 54700.0,
      "고가": 55000.0,
      "저가": 54400.0,
      "종가": 54800.0,
      "거래량": 7814322
    },
    {
      "날짜": "\"20250512\"",
      "시가": 55200.0,
      "고가": 57600.0,
      "저가": 55000.0,
      "종가": 57600.0,
      "거래량": 15414702
    },
    {
      "날짜": "\"20250513\"",
      "시가": 57700.0,
      "고가": 58200.0,
      "저가": 56800.0,
      "종가": 56900.0,
      "거래량": 16842801
    },
    {
      "날짜": "\"20250514\"",
      "시가": 57500.0,
      "고가": 57900.0,
      "저가": 57000.0,
      "종가": 57400.0,
      "거래량": 12468089
    },
    {
      "날짜": "\"20250515\"",
      "시가": 57400.0,
      "고가": 58600.0,
      "저가": 57100.0,
      "종가": 57300.0,
      "거래량": 13139736
    },
    {
      "날짜": "\"20250516\"",
      "시가": 57400.0,
      "고가": 57500.0,
      "저가": 56700.0,
      "종가": 56800.0,
      "거래량": 10385352
    },
    {
      "날짜": "\"20250519\"",
      "시가": 56400.0,
      "고가": 56400.0,
      "저가": 55500.0,
      "종가": 55800.0,
      "거래량": 9802105
    },
    {
      "날짜": "\"20250520\"",
      "시가": 56200.0,
      "고가": 56700.0,
      "저가": 55700.0,
      "종가": 55900.0,
      "거래량": 9080577
    },
    {
      "날짜": "\"20250521\"",
      "시가": 56200.0,
      "고가": 56600.0,
      "저가": 55700.0,
      "종가": 55700.0,
      "거래량": 7794181
    },
    {
      "날짜": "\"20250522\"",
      "시가": 55300.0,
      "고가": 55500.0,
      "저가": 54500.0,
      "종가": 54700.0,
      "거래량": 15254278
    },
    {
      "날짜": "\"20250523\"",
      "시가": 55000.0,
      "고가": 55200.0,
      "저가": 54100.0,
      "종가": 54200.0,
      "거래량": 11247115
    },
    {
      "날짜": "\"20250526\"",
      "시가": 53900.0,
      "고가": 55000.0,
      "저가": 53700.0,
      "종가": 54700.0,
      "거래량": 10901337
    },
    {
      "날짜": "\"20250527\"",
      "시가": 54200.0,
      "고가": 54500.0,
      "저가": 53800.0,
      "종가": 53900.0,
      "거래량": 13439520
    },
    {
      "날짜": "\"20250528\"",
      "시가": 54300.0,
      "고가": 56100.0,
      "저가": 54200.0,
      "종가": 55900.0,
      "거래량": 17516283
    },
    {
      "날짜": "\"20250529\"",
      "시가": 56200.0,
      "고가": 56400.0,
      "저가": 55600.0,
      "종가": 56100.0,
      "거래량": 12936810
    },
    {
      "날짜": "\"20250530\"",
      "시가": 56200.0,
      "고가": 57200.0,
      "저가": 55800.0,
      "종가": 56200.0,
      "거래량": 26219683
    },
    {
      "날짜": "\"20250602\"",
      "시가": 56300.0,
      "고가": 57300.0,
      "저가": 56200.0,
      "종가": 56800.0,
      "거래량": 12870515
    },
    {
      "날짜": "\"20250604\"",
      "시가": 57200.0,
      "고가": 57900.0,
      "저가": 56800.0,
      "종가": 57800.0,
      "거래량": 19649983
    },
    {
      "날짜": "\"20250605\"",
      "시가": 58100.0,
      "고가": 59900.0,
      "저가": 57900.0,
      "종가": 59100.0,
      "거래량": 23266027
    },
    {
      "날짜": "\"20250609\"",
      "시가": 60400.0,
      "고가": 60400.0,
      "저가": 59500.0,
      "종가": 59800.0,
      "거래량": 19609659
    },
    {
      "날짜": "\"20250610\"",
      "시가": 60000.0,
      "고가": 60100.0,
      "저가": 58800.0,
      "종가": 59200.0,
      "거래량": 15305760
    },
    {
      "날짜": "\"20250611\"",
      "시가": 59500.0,
      "고가": 60100.0,
      "저가": 59400.0,
      "종가": 59900.0,
      "거래량": 13610734
    },
    {
      "날짜": "\"20250612\"",
      "시가": 59700.0,
      "고가": 60000.0,
      "저가": 59300.0,
      "종가": 59500.0,
      "거래량": 17755115
    },
    {
      "날짜": "\"20250613\"",
      "시가": 60200.0,
      "고가": 60200.0,
      "저가": 57700.0,
      "종가": 58300.0,
      "거래량": 20705979
    },
    {
      "날짜": "\"20250616\"",
      "시가": 58000.0,
      "고가": 58100.0,
      "저가": 56900.0,
      "종가": 57200.0,
      "거래량": 22200872
    },
    {
      "날짜": "\"20250617\"",
      "시가": 57800.0,
      "고가": 59800.0,
      "저가": 57400.0,
      "종가": 58100.0,
      "거래량": 28637003
    },
    {
      "날짜": "\"20250618\"",
      "시가": 58000.0,
      "고가": 59800.0,
      "저가": 57900.0,
      "종가": 59800.0,
      "거래량": 17620705
    },
    {
      "날짜": "\"20250619\"",
      "시가": 60500.0,
      "고가": 60600.0,
      "저가": 59000.0,
      "종가": 59200.0,
      "거래량": 16876278
    },
    {
      "날짜": "\"20250620\"",
      "시가": 59400.0,
      "고가": 59800.0,
      "저가": 59100.0,
      "종가": 59500.0,
      "거래량": 18072251
    },
    {
      "날짜": "\"20250623\"",
      "시가": 58400.0,
      "고가": 58500.0,
      "저가": 57600.0,
      "종가": 58000.0,
      "거래량": 16551694
    },
    {
      "날짜": "\"20250624\"",
      "시가": 59400.0,
      "고가": 60600.0,
      "저가": 59300.0,
      "종가": 60500.0,
      "거래량": 23737899
    },
    {
      "날짜": "\"20250625\"",
      "시가": 61500.0,
      "고가": 61600.0,
      "저가": 60300.0,
      "종가": 61300.0,
      "거래량": 23933612
    },
    {
      "날짜": "\"20250626\"",
      "시가": 61300.0,
      "고가": 61300.0,
      "저가": 59900.0,
      "종가": 60200.0,
      "거래량": 19402300
    },
    {
      "날짜": "\"20250627\"",
      "시가": 60100.0,
      "고가": 61600.0,
      "저가": 60000.0,
      "종가": 60800.0,
      "거래량": 17340470
    },
    {
      "날짜": "\"20250630\"",
      "시가": 61200.0,
      "고가": 61200.0,
      "저가": 59800.0,
      "종가": 59800.0,
      "거래량": 17110294
    },
    {
      "날짜": "\"20250701\"",
      "시가": 60400.0,
      "고가": 61100.0,
      "저가": 60200.0,
      "종가": 60200.0,
      "거래량": 13650991
    },
    {
      "날짜": "\"20250702\"",
      "시가": 60200.0,
      "고가": 60900.0,
      "저가": 59800.0,
      "종가": 60800.0,
      "거래량": 15047951
    },
    {
      "날짜": "\"20250703\"",
      "시가": 61300.0,
      "고가": 63800.0,
      "저가": 61100.0,
      "종가": 63800.0,
      "거래량": 32040639
    },
    {
      "날짜": "\"20250704\"",
      "시가": 64700.0,
      "고가": 64700.0,
      "저가": 63000.0,
      "종가": 63300.0,
      "거래량": 23748959
    },
    {
      "날짜": "\"20250707\"",
      "시가": 62900.0,
      "고가": 63300.0,
      "저가": 61700.0,
      "종가": 61700.0,
      "거래량": 17164708
    },
    {
      "날짜": "\"20250708\"",
      "시가": 61600.0,
      "고가": 62400.0,
      "저가": 61000.0,
      "종가": 61400.0,
      "거래량": 20213724
    },
    {
      "날짜": "\"20250709\"",
      "시가": 61400.0,
      "고가": 61400.0,
      "저가": 60200.0,
      "종가": 60400.0,
      "거래량": 17533415
    },
    {
      "날짜": "\"20250710\"",
      "시가": 60600.0,
      "고가": 61200.0,
      "저가": 60400.0,
      "종가": 61000.0,
      "거래량": 14768473
    },
    {
      "날짜": "\"20250711\"",
      "시가": 61300.0,
      "고가": 62800.0,
      "저가": 61200.0,
      "종가": 62600.0,
      "거래량": 19140650
    },
    {
      "날짜": "\"20250714\"",
      "시가": 62300.0,
      "고가": 62600.0,
      "저가": 61800.0,
      "종가": 62500.0,
      "거래량": 13563846
    },
    {
      "날짜": "\"20250715\"",
      "시가": 62300.0,
      "고가": 63800.0,
      "저가": 62000.0,
      "종가": 63700.0,
      "거래량": 18442202
    },
    {
      "날짜": "\"20250716\"",
      "시가": 63700.0,
      "고가": 64700.0,
      "저가": 63100.0,
      "종가": 64700.0,
      "거래량": 23042660
    },
    {
      "날짜": "\"20250717\"",
      "시가": 65900.0,
      "고가": 66800.0,
      "저가": 64400.0,
      "종가": 66700.0,
      "거래량": 39448683
    },
    {
      "날짜": "\"20250718\"",
      "시가": 67000.0,
      "고가": 67800.0,
      "저가": 66300.0,
      "종가": 67100.0,
      "거래량": 23951531
    },
    {
      "날짜": "\"20250721\"",
      "시가": 67400.0,
      "고가": 68800.0,
      "저가": 67200.0,
      "종가": 67800.0,
      "거래량": 17723148
    },
    {
      "날짜": "\"20250722\"",
      "시가": 68100.0,
      "고가": 68500.0,
      "저가": 65600.0,
      "종가": 66000.0,
      "거래량": 20829006
    },
    {
      "날짜": "\"20250723\"",
      "시가": 66200.0,
      "고가": 66500.0,
      "저가": 64900.0,
      "종가": 66400.0,
      "거래량": 15687058
    },
    {
      "날짜": "\"20250724\"",
      "시가": 66500.0,
      "고가": 66800.0,
      "저가": 65900.0,
      "종가": 66000.0,
      "거래량": 12660193
    },
    {
      "날짜": "\"20250725\"",
      "시가": 65700.0,
      "고가": 66300.0,
      "저가": 65500.0,
      "종가": 65900.0,
      "거래량": 8045068
    }
  ]
}